LICENSE.txt
README.md
setup.py
Flask_MultiMQTT.egg-info/PKG-INFO
Flask_MultiMQTT.egg-info/SOURCES.txt
Flask_MultiMQTT.egg-info/dependency_links.txt
Flask_MultiMQTT.egg-info/requires.txt
Flask_MultiMQTT.egg-info/top_level.txt
flask_multimqtt/__init__.py
flask_multimqtt/topic.py