Metadata-Version: 2.1
Name: Flask-MultiMQTT
Version: 0.2
Summary: Flask middleware for MQTT with threading support
Home-page: https://git.sr.ht/~martijnbraam/Flask-MultiMQTT
Author: Martijn Braam
Author-email: martijn@brixit.nl
License: MIT
Platform: UNKNOWN
License-File: LICENSE.txt
